Workbook

Sheet Daily Sales Log
A1: 💧 WATER REFILLING STATION — DAILY SALES LOG
A3: Track every gallon sold, container returns, and daily income in one place.
A4: Month: | D4: April | F4: Year: | G4: 2026
A5: # | B5: Date | C5: Slim/Round Wholesale | D5: Slim/Round Regular | E5: Slim/Round Commercial | F5: Containers Returned | G5: Delivery Fee Qty | H5: Other Income | I5: TOTAL SALES (₱) | J5: Cost of Goods (₱) | K5: Operating Expenses (₱) | L5: NET PROFIT (₱) | M5: Notes
A6: 1 | I6: =IFERROR(C6*'Price List'!$C$4+D6*'Price List'!$C$5+E6*'Price List'!$C$6+F6*'Price List'!$C$7+G6*'Price List'!$C$9+H6,0) -> 0 | J6: =IFERROR(SUMPRODUCT(('Expenses Tracker'!$B$8:$B$57=B6)*('Expenses Tracker'!$D$8:$D$57="Water Supply/Chemicals")*('Expenses Tracker'!$E$8:$E$57)),0) -> 0 | K6: =IFERROR(SUMPRODUCT(('Expenses Tracker'!$B$8:$B$57=B6)*('Expenses Tracker'!$D$8:$D$57<>"Water Supply/Chemicals")*('Expenses Tracker'!$E$8:$E$57)),0) -> 0 | L6: =IFERROR(I6-J6-K6,0) -> 0
A7: 2 | I7: =IFERROR(C7*'Price List'!$C$4+D7*'Price List'!$C$5+E7*'Price List'!$C$6+F7*'Price List'!$C$7+G7*'Price List'!$C$9+H7,0) -> 0 | J7: =IFERROR(SUMPRODUCT(('Expenses Tracker'!$B$8:$B$57=B7)*('Expenses Tracker'!$D$8:$D$57="Water Supply/Chemicals")*('Expenses Tracker'!$E$8:$E$57)),0) -> 0 | K7: =IFERROR(SUMPRODUCT(('Expenses Tracker'!$B$8:$B$57=B7)*('Expenses Tracker'!$D$8:$D$57<>"Water Supply/Chemicals")*('Expenses Tracker'!$E$8:$E$57)),0) -> 0 | L7: =IFERROR(I7-J7-K7,0) -> 0
A8: 3 | I8: =IFERROR(C8*'Price List'!$C$4+D8*'Price List'!$C$5+E8*'Price List'!$C$6+F8*'Price List'!$C$7+G8*'Price List'!$C$9+H8,0) -> 0 | J8: =IFERROR(SUMPRODUCT(('Expenses Tracker'!$B$8:$B$57=B8)*('Expenses Tracker'!$D$8:$D$57="Water Supply/Chemicals")*('Expenses Tracker'!$E$8:$E$57)),0) -> 0 | K8: =IFERROR(SUMPRODUCT(('Expenses Tracker'!$B$8:$B$57=B8)*('Expenses Tracker'!$D$8:$D$57<>"Water Supply/Chemicals")*('Expenses Tracker'!$E$8:$E$57)),0) -> 0 | L8: =IFERROR(I8-J8-K8,0) -> 0
A9: 4 | I9: =IFERROR(C9*'Price List'!$C$4+D9*'Price List'!$C$5+E9*'Price List'!$C$6+F9*'Price List'!$C$7+G9*'Price List'!$C$9+H9,0) -> 0 | J9: =IFERROR(SUMPRODUCT(('Expenses Tracker'!$B$8:$B$57=B9)*('Expenses Tracker'!$D$8:$D$57="Water Supply/Chemicals")*('Expenses Tracker'!$E$8:$E$57)),0) -> 0 | K9: =IFERROR(SUMPRODUCT(('Expenses Tracker'!$B$8:$B$57=B9)*('Expenses Tracker'!$D$8:$D$57<>"Water Supply/Chemicals")*('Expenses Tracker'!$E$8:$E$57)),0) -> 0 | L9: =IFERROR(I9-J9-K9,0) -> 0
A10: 5 | I10: =IFERROR(C10*'Price List'!$C$4+D10*'Price List'!$C$5+E10*'Price List'!$C$6+F10*'Price List'!$C$7+G10*'Price List'!$C$9+H10,0) -> 0 | J10: =IFERROR(SUMPRODUCT(('Expenses Tracker'!$B$8:$B$57=B10)*('Expenses Tracker'!$D$8:$D$57="Water Supply/Chemicals")*('Expenses Tracker'!$E$8:$E$57)),0) -> 0 | K10: =IFERROR(SUMPRODUCT(('Expenses Tracker'!$B$8:$B$57=B10)*('Expenses Tracker'!$D$8:$D$57<>"Water Supply/Chemicals")*('Expenses Tracker'!$E$8:$E$57)),0) -> 0 | L10: =IFERROR(I10-J10-K10,0) -> 0
A11: 6 | I11: =IFERROR(C11*'Price List'!$C$4+D11*'Price List'!$C$5+E11*'Price List'!$C$6+F11*'Price List'!$C$7+G11*'Price List'!$C$9+H11,0) -> 0 | J11: =IFERROR(SUMPRODUCT(('Expenses Tracker'!$B$8:$B$57=B11)*('Expenses Tracker'!$D$8:$D$57="Water Supply/Chemicals")*('Expenses Tracker'!$E$8:$E$57)),0) -> 0 | K11: =IFERROR(SUMPRODUCT(('Expenses Tracker'!$B$8:$B$57=B11)*('Expenses Tracker'!$D$8:$D$57<>"Water Supply/Chemicals")*('Expenses Tracker'!$E$8:$E$57)),0) -> 0 | L11: =IFERROR(I11-J11-K11,0) -> 0
A12: 7 | I12: =IFERROR(C12*'Price List'!$C$4+D12*'Price List'!$C$5+E12*'Price List'!$C$6+F12*'Price List'!$C$7+G12*'Price List'!$C$9+H12,0) -> 0 | J12: =IFERROR(SUMPRODUCT(('Expenses Tracker'!$B$8:$B$57=B12)*('Expenses Tracker'!$D$8:$D$57="Water Supply/Chemicals")*('Expenses Tracker'!$E$8:$E$57)),0) -> 0 | K12: =IFERROR(SUMPRODUCT(('Expenses Tracker'!$B$8:$B$57=B12)*('Expenses Tracker'!$D$8:$D$57<>"Water Supply/Chemicals")*('Expenses Tracker'!$E$8:$E$57)),0) -> 0 | L12: =IFERROR(I12-J12-K12,0) -> 0
A13: 8 | I13: =IFERROR(C13*'Price List'!$C$4+D13*'Price List'!$C$5+E13*'Price List'!$C$6+F13*'Price List'!$C$7+G13*'Price List'!$C$9+H13,0) -> 0 | J13: =IFERROR(SUMPRODUCT(('Expenses Tracker'!$B$8:$B$57=B13)*('Expenses Tracker'!$D$8:$D$57="Water Supply/Chemicals")*('Expenses Tracker'!$E$8:$E$57)),0) -> 0 | K13: =IFERROR(SUMPRODUCT(('Expenses Tracker'!$B$8:$B$57=B13)*('Expenses Tracker'!$D$8:$D$57<>"Water Supply/Chemicals")*('Expenses Tracker'!$E$8:$E$57)),0) -> 0 | L13: =IFERROR(I13-J13-K13,0) -> 0
A14: 9 | I14: =IFERROR(C14*'Price List'!$C$4+D14*'Price List'!$C$5+E14*'Price List'!$C$6+F14*'Price List'!$C$7+G14*'Price List'!$C$9+H14,0) -> 0 | J14: =IFERROR(SUMPRODUCT(('Expenses Tracker'!$B$8:$B$57=B14)*('Expenses Tracker'!$D$8:$D$57="Water Supply/Chemicals")*('Expenses Tracker'!$E$8:$E$57)),0) -> 0 | K14: =IFERROR(SUMPRODUCT(('Expenses Tracker'!$B$8:$B$57=B14)*('Expenses Tracker'!$D$8:$D$57<>"Water Supply/Chemicals")*('Expenses Tracker'!$E$8:$E$57)),0) -> 0 | L14: =IFERROR(I14-J14-K14,0) -> 0
A15: 10 | I15: =IFERROR(C15*'Price List'!$C$4+D15*'Price List'!$C$5+E15*'Price List'!$C$6+F15*'Price List'!$C$7+G15*'Price List'!$C$9+H15,0) -> 0 | J15: =IFERROR(SUMPRODUCT(('Expenses Tracker'!$B$8:$B$57=B15)*('Expenses Tracker'!$D$8:$D$57="Water Supply/Chemicals")*('Expenses Tracker'!$E$8:$E$57)),0) -> 0 | K15: =IFERROR(SUMPRODUCT(('Expenses Tracker'!$B$8:$B$57=B15)*('Expenses Tracker'!$D$8:$D$57<>"Water Supply/Chemicals")*('Expenses Tracker'!$E$8:$E$57)),0) -> 0 | L15: =IFERROR(I15-J15-K15,0) -> 0
A16: 11 | I16: =IFERROR(C16*'Price List'!$C$4+D16*'Price List'!$C$5+E16*'Price List'!$C$6+F16*'Price List'!$C$7+G16*'Price List'!$C$9+H16,0) -> 0 | J16: =IFERROR(SUMPRODUCT(('Expenses Tracker'!$B$8:$B$57=B16)*('Expenses Tracker'!$D$8:$D$57="Water Supply/Chemicals")*('Expenses Tracker'!$E$8:$E$57)),0) -> 0 | K16: =IFERROR(SUMPRODUCT(('Expenses Tracker'!$B$8:$B$57=B16)*('Expenses Tracker'!$D$8:$D$57<>"Water Supply/Chemicals")*('Expenses Tracker'!$E$8:$E$57)),0) -> 0 | L16: =IFERROR(I16-J16-K16,0) -> 0
A17: 12 | I17: =IFERROR(C17*'Price List'!$C$4+D17*'Price List'!$C$5+E17*'Price List'!$C$6+F17*'Price List'!$C$7+G17*'Price List'!$C$9+H17,0) -> 0 | J17: =IFERROR(SUMPRODUCT(('Expenses Tracker'!$B$8:$B$57=B17)*('Expenses Tracker'!$D$8:$D$57="Water Supply/Chemicals")*('Expenses Tracker'!$E$8:$E$57)),0) -> 0 | K17: =IFERROR(SUMPRODUCT(('Expenses Tracker'!$B$8:$B$57=B17)*('Expenses Tracker'!$D$8:$D$57<>"Water Supply/Chemicals")*('Expenses Tracker'!$E$8:$E$57)),0) -> 0 | L17: =IFERROR(I17-J17-K17,0) -> 0
... A36: 31 | I36: =IFERROR(C36*'Price List'!$C$4+D36*'Price List'!$C$5+E36*'Price List'!$C$6+F36*'Price List'!$C$7+G36*'Price List'!$C$9+H36,0) -> 0 | J36: =IFERROR(SUMPRODUCT(('Expenses Tracker'!$B$8:$B$57=B36)*('Expenses Tracker'!$D$8:$D$57="Water Supply/Chemicals")*('Expenses Tracker'!$E$8:$E$57)),0) -> 0 | K36: =IFERROR(SUMPRODUCT(('Expenses Tracker'!$B$8:$B$57=B36)*('Expenses Tracker'!$D$8:$D$57<>"Water Supply/Chemicals")*('Expenses Tracker'!$E$8:$E$57)),0) -> 0 | L36: =IFERROR(I36-J36-K36,0) -> 0
A37: 📊 MONTHLY TOTALS | C37: =SUM(C6:C36) -> 0 | D37: =SUM(D6:D36) -> 0 | E37: =SUM(E6:E36) -> 0 | F37: =SUM(F6:F36) -> 0 | G37: =SUM(G6:G36) -> 0 | H37: =SUM(H6:H36) -> 0 | I37: =SUM(I6:I36) -> 0 | J37: =SUM(J6:J36) -> 0 | ... L37: =SUM(L6:L36) -> 0
A38: ℹ️ HOW TO USE: Enter the quantity sold each day (Cols C–H). Total Sales (Col I) auto-calculates from Price List. Cost of Goods (Col J) and Operating Expenses (Col K) auto-pull from Expenses Tracker by date. Net Profit is auto-calculated.

Sheet Expenses Tracker
A1: 💧 WATER REFILLING STATION — EXPENSES TRACKER
A3: Record all business costs here — supplies, utilities, salaries, and more.
A5: 📌 EXPENSE CATEGORIES: Water Supply/Chemicals | Electricity | Rent | Salaries | Packaging/Containers | Maintenance | Fuel/Delivery | Other
A7: # | B7: Date | C7: Description | D7: Category | E7: Amount (₱) | F7: Receipt # | G7: Notes
A8: 1
A9: 2
A10: 3
A11: 4
A12: 5
A13: 6
A14: 7
A15: 8
A16: 9
A17: 10
A18: 11
A19: 12
... A57: 50
A58: 📊 TOTAL EXPENSES | E58: =SUM(E8:E57) -> 0

Sheet Monthly Report
A1: 💧 WATER REFILLING STATION — MONTHLY PERFORMANCE REPORT
A4: METRIC | B4: Jan | C4: Feb | D4: Mar | E4: Apr | F4: May | G4: Jun | H4: Jul | I4: Aug | J4: Sep | K4: Oct | L4: Nov | M4: Dec | N4: FULL YEAR
A6: 💦 Volume Sold — Slim (gal) | N6: =SUM(B6:M6) -> 0
A7: 💦 Volume Sold — Round (gal) | N7: =SUM(B7:M7) -> 0
A8: 💦 Volume Sold — Mineral (gal) | N8: =SUM(B8:M8) -> 0
A9: 💦 Total Gallons Sold | N9: =SUM(B9:M9) -> 0
A11: 💰 Total Sales Revenue (₱) | N11: =SUM(B11:M11) -> 0
A12: 🔻 Cost of Goods Sold (₱) | N12: =SUM(B12:M12) -> 0
A13: 🔻 Operating Expenses (₱) | N13: =SUM(B13:M13) -> 0
A15: ✅ GROSS PROFIT (₱) | B15: =IFERROR(B11-B12,0) -> 0 | C15: =IFERROR(C11-C12,0) -> 0 | D15: =IFERROR(D11-D12,0) -> 0 | E15: =IFERROR(E11-E12,0) -> 0 | F15: =IFERROR(F11-F12,0) -> 0 | G15: =IFERROR(G11-G12,0) -> 0 | H15: =IFERROR(H11-H12,0) -> 0 | I15: =IFERROR(I11-I12,0) -> 0 | ... M15: =IFERROR(M11-M12,0) -> 0 | N15: =SUM(B15:M15) -> 0
A16: ✅ NET PROFIT (₱) | B16: =IFERROR(B15-B13,0) -> 0 | C16: =IFERROR(C15-C13,0) -> 0 | D16: =IFERROR(D15-D13,0) -> 0 | E16: =IFERROR(E15-E13,0) -> 0 | F16: =IFERROR(F15-F13,0) -> 0 | G16: =IFERROR(G15-G13,0) -> 0 | H16: =IFERROR(H15-H13,0) -> 0 | I16: =IFERROR(I15-I13,0) -> 0 | ... M16: =IFERROR(M15-M13,0) -> 0 | N16: =SUM(B16:M16) -> 0
A17: 📈 Profit Margin (%) | B17: =IFERROR(B16/B11,0) -> 0 | C17: =IFERROR(C16/C11,0) -> 0 | D17: =IFERROR(D16/D11,0) -> 0 | E17: =IFERROR(E16/E11,0) -> 0 | F17: =IFERROR(F16/F11,0) -> 0 | G17: =IFERROR(G16/G11,0) -> 0 | H17: =IFERROR(H16/H11,0) -> 0 | I17: =IFERROR(I16/I11,0) -> 0 | ... M17: =IFERROR(M16/M11,0) -> 0 | N17: =IFERROR(AVERAGE(B17:M17),0) -> 0
A19: 🧴 Containers Returned | N19: =SUM(B19:M19) -> 0
A20: 🚚 Delivery Trips | N20: =SUM(B20:M20) -> 0
A21: 📆 Operating Days | N21: =SUM(B21:M21) -> 0
A22: 💵 Avg Daily Revenue (₱) | N22: =SUM(B22:M22) -> 0
A23: 💵 Avg Daily Net Profit (₱) | N23: =SUM(B23:M23) -> 0
A24: ℹ️ Enter monthly figures manually in each column (Jan–Dec). Full Year column sums/averages automatically.

Sheet 📊 SUMMARY
A2: 💧 WATER REFILLING STATION — BUSINESS SUMMARY DASHBOARD
A4: Quick overview of your business performance — update the Monthly Report sheet to see changes here.
B6: 📅 This Month's Revenue | E6: 📅 This Month's Net Profit | H6: 📅 Profit Margin
B7: ='Monthly Report'!B11 -> 0 | E7: ='Monthly Report'!B16 -> 0 | H7: =IFERROR('Monthly Report'!B17,0) -> 0
B8: 📊 Full Year Revenue | E8: 📊 Full Year Net Profit | H8: 📊 Total Gallons Sold (Year)
B9: ='Monthly Report'!N11 -> 0 | E9: ='Monthly Report'!N16 -> 0 | H9: ='Monthly Report'!N9 -> 0
B11: 📈 MONTHLY BREAKDOWN
B12: Month | C12: Total Sales (₱) | D12: Net Profit (₱) | E12: Profit Margin | F12: Gallons Sold
B13: January | C13: ='Monthly Report'!B11 -> 0 | D13: ='Monthly Report'!B16 -> 0 | E13: =IFERROR('Monthly Report'!B17,0) -> 0 | F13: ='Monthly Report'!B9 -> 0
B14: February | C14: ='Monthly Report'!C11 -> 0 | D14: ='Monthly Report'!C16 -> 0 | E14: =IFERROR('Monthly Report'!C17,0) -> 0 | F14: ='Monthly Report'!C9 -> 0
B15: March | C15: ='Monthly Report'!D11 -> 0 | D15: ='Monthly Report'!D16 -> 0 | E15: =IFERROR('Monthly Report'!D17,0) -> 0 | F15: ='Monthly Report'!D9 -> 0
B16: April | C16: ='Monthly Report'!E11 -> 0 | D16: ='Monthly Report'!E16 -> 0 | E16: =IFERROR('Monthly Report'!E17,0) -> 0 | F16: ='Monthly Report'!E9 -> 0
B17: May | C17: ='Monthly Report'!F11 -> 0 | D17: ='Monthly Report'!F16 -> 0 | E17: =IFERROR('Monthly Report'!F17,0) -> 0 | F17: ='Monthly Report'!F9 -> 0
B18: June | C18: ='Monthly Report'!G11 -> 0 | D18: ='Monthly Report'!G16 -> 0 | E18: =IFERROR('Monthly Report'!G17,0) -> 0 | F18: ='Monthly Report'!G9 -> 0
B19: July | C19: ='Monthly Report'!H11 -> 0 | D19: ='Monthly Report'!H16 -> 0 | E19: =IFERROR('Monthly Report'!H17,0) -> 0 | F19: ='Monthly Report'!H9 -> 0
B20: August | C20: ='Monthly Report'!I11 -> 0 | D20: ='Monthly Report'!I16 -> 0 | E20: =IFERROR('Monthly Report'!I17,0) -> 0 | F20: ='Monthly Report'!I9 -> 0
B21: September | C21: ='Monthly Report'!J11 -> 0 | D21: ='Monthly Report'!J16 -> 0 | E21: =IFERROR('Monthly Report'!J17,0) -> 0 | F21: ='Monthly Report'!J9 -> 0
B22: October | C22: ='Monthly Report'!K11 -> 0 | D22: ='Monthly Report'!K16 -> 0 | E22: =IFERROR('Monthly Report'!K17,0) -> 0 | F22: ='Monthly Report'!K9 -> 0
B23: November | C23: ='Monthly Report'!L11 -> 0 | D23: ='Monthly Report'!L16 -> 0 | E23: =IFERROR('Monthly Report'!L17,0) -> 0 | F23: ='Monthly Report'!L9 -> 0
B24: December | C24: ='Monthly Report'!M11 -> 0 | D24: ='Monthly Report'!M16 -> 0 | E24: =IFERROR('Monthly Report'!M17,0) -> 0 | F24: ='Monthly Report'!M9 -> 0
B25: 🏁 FULL YEAR TOTAL / AVG | C25: =SUM(C13:C24) -> 0 | D25: =SUM(D13:D24) -> 0 | E25: =AVERAGE(E13:E24) -> 0 | F25: =SUM(F13:F24) -> 0
B27: 📌 HOW TO USE THIS WORKBOOK
B28: 1️⃣ Daily Sales Log | C28: Go here every day and enter gallons sold (Slim, Round, Mineral), containers returned, deliveries, and other income. Also input your daily cost of goods and expenses.
B29: 2️⃣ Expenses Tracker | C29: Log every peso you spend — water supply, electricity, rent, salaries, packaging, and other costs. One row per expense, with the date and category.
B30: 3️⃣ Monthly Report | C30: At month-end, summarize totals from the Daily Sales Log and Expenses into the corresponding month column. Formulas will auto-calculate profit and margin.
B31: 4️⃣ 📊 SUMMARY (here) | C31: This dashboard reads from the Monthly Report automatically. Your KPI cards update as soon as you fill in the Monthly Report. Share this sheet with your partners or investors for a quick overview.

Sheet Price List
A1: 💧 WATER REFILLING STATION — PRICE LIST
A3: # | B3: Product / Service | C3: Price (₱) | D3: Unit | E3: Notes
A4: 1 | B4: Slim/Round Wholesale | C4: 25 | D4: Per gallon | E4: Refill only
A5: 2 | B5: Slim/Round Regular | C5: 30 | D5: Per gallon | E5: Refill only
A6: 3 | B6: Slim/Round Commercial | C6: 35 | D6: Per gallon | E6: Refill only
A7: 4 | B7: Container Deposit (Slim) | C7: 50 | D7: Per container | E7: Refundable
A8: 5 | B8: Container Deposit (Round) | C8: 80 | D8: Per container | E8: Refundable
A9: 6 | B9: Delivery Fee | C9: 20 | D9: Per trip | E9: Within delivery area
A10: 7 | B10: Other / Special Order | C10: 10 | D10: Per unit | E10: Negotiable
